ankipandas/__init__.py
ankipandas/_columns.py
ankipandas/ankidf.py
ankipandas/collection.py
ankipandas/conftest.py
ankipandas/paths.py
ankipandas/raw.py
ankipandas/version.txt
ankipandas/data/anki_fields.csv
ankipandas/test/__init__.py
ankipandas/test/test_ankidf.py
ankipandas/test/test_collection.py
ankipandas/test/test_paths.py
ankipandas/test/test_raw.py
ankipandas/test/test_regression.py
ankipandas/test/util.py
ankipandas/test/data/few_basic_cards/collection.anki2
ankipandas/test/data/few_basic_cards/collection_v1.anki2
ankipandas/util/__init__.py
ankipandas/util/checksum.py
ankipandas/util/dataframe.py
ankipandas/util/guid.py
ankipandas/util/log.py
ankipandas/util/misc.py
ankipandas/util/types.py
ankipandas/util/test/__init__.py
ankipandas/util/test/test_dataframe.py
ankipandas/util/test/test_log.py
ankipandas/util/test/test_misc.py
ankipandas/util/test/test_types.py
ankipandas-0.3.15.dist-info/LICENSE.txt
ankipandas-0.3.15.dist-info/METADATA
ankipandas-0.3.15.dist-info/WHEEL
ankipandas-0.3.15.dist-info/top_level.txt
ankipandas-0.3.15.dist-info/RECORD
