Metadata-Version: 2.1
Name: ankipandas
Version: 0.3.15
Summary: Load your anki database as a pandas DataFrame with just one line of code!
Home-page: https://github.com/klieret/ankipandas
License: MIT
Project-URL: Bug Tracker, https://github.com/klieret/ankipandas/issues
Project-URL: Documentation, https://ankipandas.readthedocs.io/
Project-URL: Source Code, https://github.com/klieret/ankipandas/
Keywords: anki,pandas,dataframe
Classifier: Programming Language :: Python :: 3
Classifier: Programming Language :: Python :: 3.7
Classifier: Programming Language :: Python :: 3.8
Classifier: Programming Language :: Python :: 3.9
Classifier: Programming Language :: Python :: 3.10
Classifier: License :: OSI Approved :: MIT License
Classifier: Operating System :: OS Independent
Classifier: Topic :: Database
Classifier: Topic :: Education
Classifier: Topic :: Utilities
License-File: LICENSE.txt
Requires-Dist: pandas
Requires-Dist: colorlog
Requires-Dist: randomfiletree
Requires-Dist: numpy
